tensorflow_play/__init__.py
tensorflow_play-0.0.1.dist-info/LICENSE
tensorflow_play-0.0.1.dist-info/METADATA
tensorflow_play-0.0.1.dist-info/WHEEL
tensorflow_play-0.0.1.dist-info/top_level.txt
tensorflow_play-0.0.1.dist-info/RECORD
