Metadata-Version: 2.1
Name: tensorflow-play
Version: 0.0.1
Summary: The lightweight engineering TensorFlow wrapper for AI engineer. Write less, Reuse more, Scale easily.
Home-page: https://github.com/Marcnuth/tensorflow-play
Author: Marcnuth
Author-email: hxianxian@gmail.com
License: Apache License 2.0
Platform: UNKNOWN
Classifier: Topic :: Scientific/Engineering :: Artificial Intelligence
Classifier: Topic :: Software Development :: Libraries
Classifier: Programming Language :: Python :: 3
Requires-Dist: tensorflow (>=r2.0)
Requires-Dist: numpy
Requires-Dist: spacy
Requires-Dist: Pillow
Requires-Dist: opencv-python
Requires-Dist: pathlib
